pygitversion/__init__.py
pygitversion/tests/test_pygitversion.py
pygitversion-1.0.1.dist-info/AUTHORS.rst
pygitversion-1.0.1.dist-info/LICENSE
pygitversion-1.0.1.dist-info/METADATA
pygitversion-1.0.1.dist-info/WHEEL
pygitversion-1.0.1.dist-info/top_level.txt
pygitversion-1.0.1.dist-info/RECORD
