Metadata-Version: 2.1
Name: pygitversion
Version: 1.0.1
Summary: A set of plugins for setuptools_scm to enable better version tracking
Home-page: https://github.com/RadioAstronomySoftwareGroup/pygitversion
Author: Radio Astronomy Software Group
Author-email: steven.g.murray@asu.edu
License: MIT
Project-URL: Documentation, https://pygitversion.readthedocs.io/
Project-URL: Changelog, https://pygitversion.readthedocs.io/en/latest/changelog.html
Project-URL: Issue Tracker, https://github.com/RadioAstronomySoftwareGroup/pygitversion/issues
Platform: UNKNOWN
Classifier: Development Status :: 5 - Production/Stable
Classifier: Intended Audience :: Developers
Classifier: License :: OSI Approved :: MIT License
Classifier: Operating System :: Unix
Classifier: Operating System :: POSIX
Classifier: Operating System :: Microsoft :: Windows
Classifier: Programming Language :: Python
Classifier: Programming Language :: Python :: 3
Classifier: Programming Language :: Python :: 3.6
Classifier: Programming Language :: Python :: 3.7
Classifier: Programming Language :: Python :: Implementation :: CPython
Classifier: Topic :: Utilities
Requires-Python: >=3.5
Requires-Dist: setuptools-scm
Provides-Extra: dev
Requires-Dist: pre-commit ; extra == 'dev'
Requires-Dist: tox ; extra == 'dev'
Requires-Dist: pytest ; extra == 'dev'
Requires-Dist: black ; extra == 'dev'
Requires-Dist: twine ; extra == 'dev'
